pyclothoids/__init__.py
pyclothoids/_clothoids_cpp.cp312-win_amd64.pyd
pyclothoids/clothoid.py
pyclothoids-0.2.0.dist-info/licenses/LICENSE
pyclothoids-0.2.0.dist-info/METADATA
pyclothoids-0.2.0.dist-info/WHEEL
pyclothoids-0.2.0.dist-info/top_level.txt
pyclothoids-0.2.0.dist-info/RECORD
