Metadata-Version: 2.4
Name: pyclothoids
Version: 0.2.0
Summary: A library for clothoid curves in Python
Home-page: https://github.com/phillipd94/PyClothoids
Author: Phillip Dix
Author-email: phildix11@gmail.com
License-File: LICENSE
Requires-Dist: pybind11>=2.4
Dynamic: author
Dynamic: author-email
Dynamic: description
Dynamic: description-content-type
Dynamic: home-page
Dynamic: license-file
Dynamic: requires-dist
Dynamic: summary
